lib/__init__.py
lib/data/__init__.py
lib/data/db.py
lib/services/__init__.py
lib/services/shopify_init.py
lib/utils/__init__.py
lib/utils/dictionary_helper.py
lib/utils/webhook_verify.py
Flask_Shopify_Integration_Library-0.0.3.dist-info/METADATA
Flask_Shopify_Integration_Library-0.0.3.dist-info/WHEEL
Flask_Shopify_Integration_Library-0.0.3.dist-info/top_level.txt
Flask_Shopify_Integration_Library-0.0.3.dist-info/RECORD
