Metadata-Version: 2.1
Name: Flask-Shopify-Integration-Library
Version: 0.0.3
Summary: UNKNOWN
Home-page: UNKNOWN
Author: UNKNOWN
Author-email: UNKNOWN
License: UNKNOWN
Platform: 
Requires-Dist: Flask (==2.0.3)
Requires-Dist: flask-marshmallow (==0.10.1)
Requires-Dist: Flask-SQLAlchemy (==2.4.1)
Requires-Dist: marshmallow (==3.3.0)
Requires-Dist: marshmallow-sqlalchemy (==0.21.0)
Requires-Dist: python-dotenv (==0.10.3)
Requires-Dist: ShopifyAPI (==12.4.0)
Requires-Dist: SQLAlchemy (==1.3.13)
